{
  "annotations": {
    "list": [
      {
        "builtIn": 1,
        "datasource": {
          "type": "grafana",
          "uid": "-- Grafana --"
        },
        "enable": true,
        "hide": true,
        "iconColor": "rgba(0, 211, 255, 1)",
        "name": "Annotations & Alerts",
        "type": "dashboard"
      }
    ]
  },
  "description": "Monitors the compute infrastructure by CPU usage, RAM, and disk space",
  "editable": true,
  "fiscalYearStartMonth": 0,
  "graphTooltip": 0,
  "id": 3,
  "links": [],
  "panels": [
    {
      "datasource": {
        "type": "prometheus",
        "uid": "promID"
      },
      "fieldConfig": {
        "defaults": {
          "color": {
            "mode": "thresholds"
          },
          "mappings": [],
          "thresholds": {
            "mode": "absolute",
            "steps": [
              {
                "color": "green",
                "value": 0
              },
              {
                "color": "red",
                "value": 80
              }
            ]
          },
          "unit": "percentunit"
        },
        "overrides": []
      },
      "gridPos": {
        "h": 6,
        "w": 5,
        "x": 0,
        "y": 0
      },
      "id": 1,
      "options": {
        "minVizHeight": 75,
        "minVizWidth": 75,
        "orientation": "auto",
        "reduceOptions": {
          "calcs": [
            "lastNotNull"
          ],
          "fields": "",
          "values": false
        },
        "showThresholdLabels": false,
        "showThresholdMarkers": true,
        "sizing": "auto"
      },
      "pluginVersion": "12.3.1",
      "targets": [
        {
          "datasource": {
            "type": "prometheus",
            "uid": "promID"
          },
          "editorMode": "code",
          "expr": "1 - (avg by (instance) (rate(node_cpu_seconds_total{mode=\"idle\"}[5m])))",
          "legendFormat": "__auto",
          "range": true,
          "refId": "A"
        }
      ],
      "title": "CPU Usage",
      "type": "gauge"
    },
    {
      "datasource": {
        "type": "prometheus",
        "uid": "promID"
      },
      "fieldConfig": {
        "defaults": {
          "color": {
            "mode": "thresholds"
          },
          "mappings": [],
          "thresholds": {
            "mode": "absolute",
            "steps": [
              {
                "color": "green",
                "value": 0
              },
              {
                "color": "red",
                "value": 80
              }
            ]
          },
          "unit": "percentunit"
        },
        "overrides": []
      },
      "gridPos": {
        "h": 6,
        "w": 5,
        "x": 5,
        "y": 0
      },
      "id": 2,
      "options": {
        "minVizHeight": 75,
        "minVizWidth": 75,
        "orientation": "auto",
        "reduceOptions": {
          "calcs": [
            "lastNotNull"
          ],
          "fields": "",
          "values": false
        },
        "showThresholdLabels": false,
        "showThresholdMarkers": true,
        "sizing": "auto"
      },
      "pluginVersion": "12.3.1",
      "targets": [
        {
          "editorMode": "code",
          "expr": "1 - node_memory_MemAvailable_bytes / node_memory_MemTotal_bytes",
          "legendFormat": "__auto",
          "range": true,
          "refId": "A"
        }
      ],
      "title": "RAM Usage",
      "type": "gauge"
    },
    {
      "datasource": {
        "type": "prometheus",
        "uid": "promID"
      },
      "fieldConfig": {
        "defaults": {
          "color": {
            "mode": "thresholds"
          },
          "mappings": [],
          "thresholds": {
            "mode": "absolute",
            "steps": [
              {
                "color": "green",
                "value": 0
              },
              {
                "color": "red",
                "value": 80
              }
            ]
          },
          "unit": "percentunit"
        },
        "overrides": []
      },
      "gridPos": {
        "h": 6,
        "w": 5,
        "x": 10,
        "y": 0
      },
      "id": 3,
      "options": {
        "minVizHeight": 75,
        "minVizWidth": 75,
        "orientation": "auto",
        "reduceOptions": {
          "calcs": [
            "lastNotNull"
          ],
          "fields": "",
          "values": false
        },
        "showThresholdLabels": false,
        "showThresholdMarkers": true,
        "sizing": "auto"
      },
      "pluginVersion": "12.3.1",
      "targets": [
        {
          "editorMode": "code",
          "expr": "1 - sum(node_filesystem_avail_bytes{fstype!=\"tmpfs\"}) / sum(node_filesystem_size_bytes{fstype!=\"tmpfs\"})",
          "legendFormat": "__auto",
          "range": true,
          "refId": "A"
        }
      ],
      "title": "Disk Usage",
      "type": "gauge"
    }
  ],
  "preload": false,
  "schemaVersion": 42,
  "tags": [],
  "templating": {
    "list": []
  },
  "time": {
    "from": "now-6h",
    "to": "now"
  },
  "timepicker": {},
  "timezone": "browser",
  "title": "Infrastructure Overview",
  "uid": "infra_overview_dashboard",
  "version": 3
}